setup.py
rt_probability/Binomialdistribution.py
rt_probability/Gaussiandistribution.py
rt_probability/Generaldistribution.py
rt_probability/__init__.py
rt_probability.egg-info/PKG-INFO
rt_probability.egg-info/SOURCES.txt
rt_probability.egg-info/dependency_links.txt
rt_probability.egg-info/not-zip-safe
rt_probability.egg-info/top_level.txt