Metadata-Version: 1.0
Name: rt-probability
Version: 1.0
Summary: Gaussian and Binomial distributions
Home-page: UNKNOWN
Author: Ravi T.
Author-email: UNKNOWN
License: UNKNOWN
Platform: UNKNOWN
